ctrlchandler/LICENSE
ctrlchandler/README.MD
ctrlchandler/__init__.py
ctrlchandler/requirements.txt
ctrlchandler/thirdparty.json
ctrlchandler-0.10.dist-info/LICENSE.rst
ctrlchandler-0.10.dist-info/METADATA
ctrlchandler-0.10.dist-info/WHEEL
ctrlchandler-0.10.dist-info/top_level.txt
ctrlchandler-0.10.dist-info/RECORD
