Metadata-Version: 2.1
Name: ctrlchandler
Version: 0.10
Summary: Like atexit but for ctrl+c
Home-page: https://github.com/hansalemaos/ctrlchandler
Author: Johannes Fischer
Author-email: <aulasparticularesdealemaosp@gmail.com>
License: MIT
Keywords: atexit,ctypes,kill,terminate
Classifier: Development Status :: 4 - Beta
Classifier: Programming Language :: Python :: 3 :: Only
Classifier: Programming Language :: Python :: 3.10
Classifier: Topic :: Scientific/Engineering :: Visualization
Classifier: Topic :: Software Development :: Libraries :: Python Modules
Classifier: Topic :: Utilities
License-File: LICENSE.rst
